{
    "job": "build",
    "ref": "refs/heads/main",
    "sha": "82a7287281b4067dbbe0a8d77a7f6869bbc783f5",
    "repository": "ResiSense/ResiSense.github.io",
    "repository_Url": null,
    "run_id": "10114967595",
    "run_number": "77",
    "run_attempt": "1",
    "artifact_cache_size_limit": "10",
    "actor": "CCheukKa",
    "trigerring_actor": null,
    "workflow": "Full CI Pipeline",
    "event_name": "push",
    "event": {
        "after": "82a7287281b4067dbbe0a8d77a7f6869bbc783f5",
        "before": "92f319b1c94094c8366fb912fabf3d85904f94c8",
        "commits": [
            {
                "author": {
                    "email": "ccheukka@gmail.com",
                    "name": "CCheukKa",
                    "username": "CCheukKa"
                },
                "committer": {
                    "email": "ccheukka@gmail.com",
                    "name": "CCheukKa",
                    "username": "CCheukKa"
                },
                "distinct": true,
                "id": "82a7287281b4067dbbe0a8d77a7f6869bbc783f5",
                "message": "update TODO.md",
                "timestamp": "2024-07-27T01:06:09+08:00",
                "tree_id": "018e86253b90d3d6a1e188436e8c8911a8e56838",
                "url": "https://github.com/ResiSense/ResiSense.github.io/commit/82a7287281b4067dbbe0a8d77a7f6869bbc783f5"
            }
        ],
        "compare": "https://github.com/ResiSense/ResiSense.github.io/compare/92f319b1c940...82a7287281b4",
        "created": false,
        "deleted": false,
        "forced": false,
        "head_commit": {
            "author": {
                "email": "ccheukka@gmail.com",
                "name": "CCheukKa",
                "username": "CCheukKa"
            },
            "committer": {
                "email": "ccheukka@gmail.com",
                "name": "CCheukKa",
                "username": "CCheukKa"
            },
            "distinct": true,
            "id": "82a7287281b4067dbbe0a8d77a7f6869bbc783f5",
            "message": "update TODO.md",
            "timestamp": "2024-07-27T01:06:09+08:00",
            "tree_id": "018e86253b90d3d6a1e188436e8c8911a8e56838",
            "url": "https://github.com/ResiSense/ResiSense.github.io/commit/82a7287281b4067dbbe0a8d77a7f6869bbc783f5"
        },
        "pusher": {
            "email": "ccheukka@gmail.com",
            "name": "CCheukKa"
        },
        "ref": "refs/heads/main"
    },
    "ref_name": "main",
    "ref_protected": false,
    "ref_type": "branch",
    "secret_source": "Actions",
    "workflow_ref": "ResiSense/ResiSense.github.io/.github/workflows/full-ci-pipeline.yaml@refs/heads/main",
    "workflow_sha": "82a7287281b4067dbbe0a8d77a7f6869bbc783f5",
    "workspace": "/home/runner/work/ResiSense.github.io/ResiSense.github.io"
}
